oceanbench/__init__.py
oceanbench/core/climate_forecast_standard_names.py
oceanbench/core/dataset_utils.py
oceanbench/core/derived_quantities.py
oceanbench/core/environment_variables.py
oceanbench/core/evaluate.py
oceanbench/core/geostrophic_currents.py
oceanbench/core/lagrangian_trajectory.py
oceanbench/core/lead_day_utils.py
oceanbench/core/metrics.py
oceanbench/core/mixed_layer_depth.py
oceanbench/core/python2jupyter.py
oceanbench/core/references/glorys.py
oceanbench/core/rmsd.py
oceanbench/core/templates/evaluation_template.py
oceanbench/core/templates/evaluation_template.py.license
oceanbench/core/version.py
oceanbench/metrics.py
oceanbench-0.0.2.dist-info/LICENSES/EUPL-1.2.txt
oceanbench-0.0.2.dist-info/METADATA
oceanbench-0.0.2.dist-info/WHEEL
oceanbench-0.0.2.dist-info/RECORD
