Metadata-Version: 2.3
Name: oceanbench
Version: 0.0.2
Summary: 
Author: Mercator Ocean International
Author-email: digital-ocean-dev@mercator-ocean.eu
Requires-Python: >=3.12.9
Classifier: Programming Language :: Python :: 3
Classifier: Programming Language :: Python :: 3.13
Requires-Dist: aiohttp (>=3.0.0)
Requires-Dist: copernicusmarine (==2.0.1)
Requires-Dist: dask (>=2022)
Requires-Dist: gsw (>=3.6.19,<4.0.0)
Requires-Dist: jupyter (>=1.1)
Requires-Dist: matplotlib (>=3.10.0,<4.0.0)
Requires-Dist: netcdf4 (>=1.7.2,<2.0.0)
Requires-Dist: numcodecs (==0.15.1)
Requires-Dist: papermill[s3] (>=2.6.0)
Requires-Dist: parcels (>=3.1.2,<4.0.0)
Requires-Dist: requests (>=2.27.1)
Requires-Dist: seaborn (>=0.13.2,<0.14.0)
Requires-Dist: xarray (==2025.1.2)
Requires-Dist: zarr (==2.18.4)
